{"box_data": [{"position": {"minX": 291.7109375, "minY": 167.509765625, "maxX": 310.0234375, "maxY": 178.361328125}, "class_id": 0, "box_caption": "%s %.3f", "scores": {"class_score": 172.875}, "domain": "pixel"}, {"position": {"minX": 566.296875, "minY": 273.0234375, "maxX": 579.890625, "maxY": 287.1640625}, "class_id": 0, "box_caption": "%s %.3f", "scores": {"class_score": 284.5}, "domain": "pixel"}, {"position": {"minX": 586.53515625, "minY": 367.53125, "maxX": 600.27734375, "maxY": 385.0}, "class_id": 0, "box_caption": "%s %.3f", "scores": {"class_score": 381.5}, "domain": "pixel"}, {"position": {"minX": 537.46484375, "minY": 241.75390625, "maxX": 552.41015625, "maxY": 253.44921875}, "class_id": 0, "box_caption": "%s %.3f", "scores": {"class_score": 244.75}, "domain": "pixel"}, {"position": {"minX": 8.166015625, "minY": 403.15234375, "maxX": 22.275390625, "maxY": 419.05859375}, "class_id": 0, "box_caption": "%s %.3f", "scores": {"class_score": 407.25}, "domain": "pixel"}, {"position": {"minX": 536.27734375, "minY": 240.5390625, "maxX": 548.72265625, "maxY": 251.2109375}, "class_id": 0, "box_caption": "%s %.3f", "scores": {"class_score": 245.25}, "domain": "pixel"}, {"position": {"minX": 528.34375, "minY": 241.75, "maxX": 604.78125, "maxY": 292.375}, "class_id": 1, "box_caption": "%s %.3f", "scores": {"class_score": 264.25}, "domain": "pixel"}, {"position": {"minX": 505.765625, "minY": 260.4375, "maxX": 539.359375, "maxY": 279.8125}, "class_id": 0, "box_caption": "%s %.3f", "scores": {"class_score": 267.5}, "domain": "pixel"}, {"position": {"minX": 515.0, "minY": 232.5625, "maxX": 611.875, "maxY": 301.5625}, "class_id": 0, "box_caption": "%s %.3f", "scores": {"class_score": 262.5}, "domain": "pixel"}, {"position": {"minX": 581.125, "minY": 370.0546875, "maxX": 596.5, "maxY": 388.6953125}, "class_id": 0, "box_caption": "%s %.3f", "scores": {"class_score": 383.75}, "domain": "pixel"}, {"position": {"minX": 634.177734375, "minY": 367.9296875, "maxX": 639.322265625, "maxY": 385.5703125}, "class_id": 0, "box_caption": "%s %.3f", "scores": {"class_score": 369.5}, "domain": "pixel"}, {"position": {"minX": 635.87890625, "minY": 369.1796875, "maxX": 640.44921875, "maxY": 385.5859375}, "class_id": 0, "box_caption": "%s %.3f", "scores": {"class_score": 375.75}, "domain": "pixel"}, {"position": {"minX": 2.296875, "minY": 409.0390625, "maxX": 25.703125, "maxY": 430.2421875}, "class_id": 0, "box_caption": "%s %.3f", "scores": {"class_score": 416.0}, "domain": "pixel"}, {"position": {"minX": 538.3515625, "minY": 212.4140625, "maxX": 554.8984375, "maxY": 228.4609375}, "class_id": 0, "box_caption": "%s %.3f", "scores": {"class_score": 212.5}, "domain": "pixel"}, {"position": {"minX": 537.25, "minY": 227.8828125, "maxX": 555.59375, "maxY": 246.6796875}, "class_id": 0, "box_caption": "%s %.3f", "scores": {"class_score": 232.5}, "domain": "pixel"}], "class_labels": {"0": "Ant"}}