{"box_data": [{"position": {"minX": 385.115234375, "minY": 604.9765625, "maxX": 395.771484375, "maxY": 624.5859375}, "class_id": 0, "box_caption": "%s %.3f", "scores": {"class_score": 617.0}, "domain": "pixel"}, {"position": {"minX": 382.62890625, "minY": 602.5625, "maxX": 394.40234375, "maxY": 622.015625}, "class_id": 0, "box_caption": "%s %.3f", "scores": {"class_score": 613.0}, "domain": "pixel"}, {"position": {"minX": 386.828125, "minY": 607.76953125, "maxX": 399.203125, "maxY": 629.66015625}, "class_id": 0, "box_caption": "%s %.3f", "scores": {"class_score": 619.5}, "domain": "pixel"}, {"position": {"minX": 511.625, "minY": 162.984375, "maxX": 523.484375, "maxY": 178.8984375}, "class_id": 0, "box_caption": "%s %.3f", "scores": {"class_score": 168.125}, "domain": "pixel"}, {"position": {"minX": 427.8046875, "minY": 541.421875, "maxX": 439.578125, "maxY": 557.75}, "class_id": 0, "box_caption": "%s %.3f", "scores": {"class_score": 547.5}, "domain": "pixel"}, {"position": {"minX": 427.2734375, "minY": 543.8515625, "maxX": 438.40625, "maxY": 563.3828125}, "class_id": 0, "box_caption": "%s %.3f", "scores": {"class_score": 552.5}, "domain": "pixel"}, {"position": {"minX": 390.6796875, "minY": 614.65625, "maxX": 402.0390625, "maxY": 635.390625}, "class_id": 0, "box_caption": "%s %.3f", "scores": {"class_score": 624.0}, "domain": "pixel"}, {"position": {"minX": 409.91015625, "minY": 602.8671875, "maxX": 420.93359375, "maxY": 620.7109375}, "class_id": 0, "box_caption": "%s %.3f", "scores": {"class_score": 608.5}, "domain": "pixel"}, {"position": {"minX": 406.6171875, "minY": 616.0234375, "maxX": 417.7890625, "maxY": 638.0546875}, "class_id": 0, "box_caption": "%s %.3f", "scores": {"class_score": 627.0}, "domain": "pixel"}, {"position": {"minX": 407.546875, "minY": 611.015625, "maxX": 418.375, "maxY": 629.96875}, "class_id": 0, "box_caption": "%s %.3f", "scores": {"class_score": 619.0}, "domain": "pixel"}, {"position": {"minX": 525.99609375, "minY": 54.59375, "maxX": 536.62109375, "maxY": 71.25}, "class_id": 0, "box_caption": "%s %.3f", "scores": {"class_score": 61.78125}, "domain": "pixel"}, {"position": {"minX": 420.61328125, "minY": 567.74609375, "maxX": 431.48828125, "maxY": 586.44921875}, "class_id": 0, "box_caption": "%s %.3f", "scores": {"class_score": 572.5}, "domain": "pixel"}, {"position": {"minX": 395.27734375, "minY": 618.28125, "maxX": 408.04296875, "maxY": 640.4375}, "class_id": 0, "box_caption": "%s %.3f", "scores": {"class_score": 631.0}, "domain": "pixel"}, {"position": {"minX": 412.5859375, "minY": 600.296875, "maxX": 423.71875, "maxY": 618.59375}, "class_id": 0, "box_caption": "%s %.3f", "scores": {"class_score": 605.0}, "domain": "pixel"}, {"position": {"minX": 420.69921875, "minY": 563.59375, "maxX": 431.48828125, "maxY": 581.0625}, "class_id": 0, "box_caption": "%s %.3f", "scores": {"class_score": 568.5}, "domain": "pixel"}, {"position": {"minX": 380.59375, "minY": 600.90234375, "maxX": 392.390625, "maxY": 619.19921875}, "class_id": 0, "box_caption": "%s %.3f", "scores": {"class_score": 608.0}, "domain": "pixel"}, {"position": {"minX": 396.640625, "minY": 613.1328125, "maxX": 406.4453125, "maxY": 630.6171875}, "class_id": 0, "box_caption": "%s %.3f", "scores": {"class_score": 625.0}, "domain": "pixel"}, {"position": {"minX": 418.7109375, "minY": 570.2109375, "maxX": 429.6640625, "maxY": 588.6796875}, "class_id": 0, "box_caption": "%s %.3f", "scores": {"class_score": 574.5}, "domain": "pixel"}, {"position": {"minX": 426.9296875, "minY": 550.45703125, "maxX": 438.3203125, "maxY": 570.87890625}, "class_id": 0, "box_caption": "%s %.3f", "scores": {"class_score": 559.5}, "domain": "pixel"}, {"position": {"minX": 431.6796875, "minY": 536.73046875, "maxX": 442.3828125, "maxY": 551.80078125}, "class_id": 0, "box_caption": "%s %.3f", "scores": {"class_score": 541.0}, "domain": "pixel"}, {"position": {"minX": 411.30078125, "minY": 608.09765625, "maxX": 422.28515625, "maxY": 627.98828125}, "class_id": 0, "box_caption": "%s %.3f", "scores": {"class_score": 615.5}, "domain": "pixel"}, {"position": {"minX": 413.45703125, "minY": 593.97265625, "maxX": 425.30078125, "maxY": 613.09765625}, "class_id": 0, "box_caption": "%s %.3f", "scores": {"class_score": 597.5}, "domain": "pixel"}, {"position": {"minX": 419.5859375, "minY": 576.08203125, "maxX": 430.3046875, "maxY": 594.53515625}, "class_id": 0, "box_caption": "%s %.3f", "scores": {"class_score": 581.0}, "domain": "pixel"}, {"position": {"minX": 409.34765625, "minY": 615.95703125, "maxX": 419.92578125, "maxY": 636.59765625}, "class_id": 0, "box_caption": "%s %.3f", "scores": {"class_score": 626.0}, "domain": "pixel"}, {"position": {"minX": 575.4765625, "minY": 55.4453125, "maxX": 586.1328125, "maxY": 72.0390625}, "class_id": 0, "box_caption": "%s %.3f", "scores": {"class_score": 61.9375}, "domain": "pixel"}, {"position": {"minX": 380.390625, "minY": 598.33203125, "maxX": 390.625, "maxY": 613.98046875}, "class_id": 0, "box_caption": "%s %.3f", "scores": {"class_score": 606.0}, "domain": "pixel"}, {"position": {"minX": 396.984375, "minY": 623.25390625, "maxX": 409.984375, "maxY": 642.08203125}, "class_id": 0, "box_caption": "%s %.3f", "scores": {"class_score": 630.5}, "domain": "pixel"}, {"position": {"minX": 416.921875, "minY": 578.37890625, "maxX": 428.875, "maxY": 597.59765625}, "class_id": 0, "box_caption": "%s %.3f", "scores": {"class_score": 582.0}, "domain": "pixel"}, {"position": {"minX": 423.08984375, "minY": 552.98828125, "maxX": 435.26953125, "maxY": 573.75390625}, "class_id": 0, "box_caption": "%s %.3f", "scores": {"class_score": 559.5}, "domain": "pixel"}, {"position": {"minX": 404.09375, "minY": 622.21875, "maxX": 416.5, "maxY": 641.921875}, "class_id": 0, "box_caption": "%s %.3f", "scores": {"class_score": 630.5}, "domain": "pixel"}, {"position": {"minX": 529.244140625, "minY": 53.76953125, "maxX": 540.759765625, "maxY": 69.57421875}, "class_id": 0, "box_caption": "%s %.3f", "scores": {"class_score": 61.34375}, "domain": "pixel"}, {"position": {"minX": 415.5078125, "minY": 585.71875, "maxX": 427.4140625, "maxY": 605.265625}, "class_id": 0, "box_caption": "%s %.3f", "scores": {"class_score": 589.5}, "domain": "pixel"}, {"position": {"minX": 386.712890625, "minY": 600.19140625, "maxX": 396.798828125, "maxY": 615.32421875}, "class_id": 0, "box_caption": "%s %.3f", "scores": {"class_score": 607.0}, "domain": "pixel"}, {"position": {"minX": 526.5390625, "minY": 51.12109375, "maxX": 536.625, "maxY": 65.94140625}, "class_id": 0, "box_caption": "%s %.3f", "scores": {"class_score": 58.5}, "domain": "pixel"}, {"position": {"minX": 418.408203125, "minY": 583.62890625, "maxX": 429.181640625, "maxY": 602.09765625}, "class_id": 0, "box_caption": "%s %.3f", "scores": {"class_score": 588.5}, "domain": "pixel"}, {"position": {"minX": 425.943359375, "minY": 560.50390625, "maxX": 437.279296875, "maxY": 579.26953125}, "class_id": 0, "box_caption": "%s %.3f", "scores": {"class_score": 567.5}, "domain": "pixel"}, {"position": {"minX": 295.21875, "minY": 604.015625, "maxX": 304.796875, "maxY": 620.09375}, "class_id": 0, "box_caption": "%s %.3f", "scores": {"class_score": 611.0}, "domain": "pixel"}, {"position": {"minX": 294.90625, "minY": 609.03125, "maxX": 304.8984375, "maxY": 626.015625}, "class_id": 0, "box_caption": "%s %.3f", "scores": {"class_score": 616.5}, "domain": "pixel"}, {"position": {"minX": 508.3984375, "minY": 162.26953125, "maxX": 520.0546875, "maxY": 178.42578125}, "class_id": 0, "box_caption": "%s %.3f", "scores": {"class_score": 168.875}, "domain": "pixel"}, {"position": {"minX": 379.21875, "minY": 606.18359375, "maxX": 392.03125, "maxY": 625.27734375}, "class_id": 0, "box_caption": "%s %.3f", "scores": {"class_score": 613.5}, "domain": "pixel"}, {"position": {"minX": 530.81640625, "minY": 55.86328125, "maxX": 544.16015625, "maxY": 73.70703125}, "class_id": 0, "box_caption": "%s %.3f", "scores": {"class_score": 63.0625}, "domain": "pixel"}, {"position": {"minX": 416.822265625, "minY": 592.62109375, "maxX": 427.900390625, "maxY": 610.65234375}, "class_id": 0, "box_caption": "%s %.3f", "scores": {"class_score": 597.5}, "domain": "pixel"}, {"position": {"minX": 513.74609375, "minY": 161.3828125, "maxX": 524.81640625, "maxY": 176.6484375}, "class_id": 0, "box_caption": "%s %.3f", "scores": {"class_score": 166.25}, "domain": "pixel"}, {"position": {"minX": 433.470703125, "minY": 538.27734375, "maxX": 443.900390625, "maxY": 553.90234375}, "class_id": 0, "box_caption": "%s %.3f", "scores": {"class_score": 544.0}, "domain": "pixel"}, {"position": {"minX": 565.890625, "minY": 26.4921875, "maxX": 575.7734375, "maxY": 41.2421875}, "class_id": 0, "box_caption": "%s %.3f", "scores": {"class_score": 32.25}, "domain": "pixel"}, {"position": {"minX": 383.03125, "minY": 594.73828125, "maxX": 393.6875, "maxY": 608.94921875}, "class_id": 0, "box_caption": "%s %.3f", "scores": {"class_score": 601.0}, "domain": "pixel"}, {"position": {"minX": 397.51171875, "minY": 606.90625, "maxX": 405.96484375, "maxY": 622.203125}, "class_id": 0, "box_caption": "%s %.3f", "scores": {"class_score": 617.5}, "domain": "pixel"}, {"position": {"minX": 294.015625, "minY": 617.265625, "maxX": 303.8984375, "maxY": 635.15625}, "class_id": 0, "box_caption": "%s %.3f", "scores": {"class_score": 626.0}, "domain": "pixel"}, {"position": {"minX": 571.8828125, "minY": 54.4765625, "maxX": 581.6171875, "maxY": 69.5078125}, "class_id": 0, "box_caption": "%s %.3f", "scores": {"class_score": 61.40625}, "domain": "pixel"}, {"position": {"minX": 420.3203125, "minY": 556.4375, "maxX": 431.8359375, "maxY": 573.78125}, "class_id": 0, "box_caption": "%s %.3f", "scores": {"class_score": 563.5}, "domain": "pixel"}, {"position": {"minX": 295.6015625, "minY": 599.3359375, "maxX": 305.2890625, "maxY": 615.2109375}, "class_id": 0, "box_caption": "%s %.3f", "scores": {"class_score": 605.5}, "domain": "pixel"}, {"position": {"minX": 572.24609375, "minY": 56.89453125, "maxX": 583.44140625, "maxY": 73.12890625}, "class_id": 0, "box_caption": "%s %.3f", "scores": {"class_score": 63.71875}, "domain": "pixel"}, {"position": {"minX": 300.80078125, "minY": 610.7265625, "maxX": 310.92578125, "maxY": 627.7734375}, "class_id": 0, "box_caption": "%s %.3f", "scores": {"class_score": 619.0}, "domain": "pixel"}, {"position": {"minX": 298.712890625, "minY": 604.8671875, "maxX": 308.431640625, "maxY": 620.8984375}, "class_id": 0, "box_caption": "%s %.3f", "scores": {"class_score": 613.0}, "domain": "pixel"}, {"position": {"minX": 435.43359375, "minY": 533.0546875, "maxX": 444.68359375, "maxY": 547.2265625}, "class_id": 0, "box_caption": "%s %.3f", "scores": {"class_score": 538.5}, "domain": "pixel"}, {"position": {"minX": 425.8984375, "minY": 536.63671875, "maxX": 437.7421875, "maxY": 551.84765625}, "class_id": 0, "box_caption": "%s %.3f", "scores": {"class_score": 544.0}, "domain": "pixel"}, {"position": {"minX": 508.02734375, "minY": 158.65625, "maxX": 518.20703125, "maxY": 174.1875}, "class_id": 0, "box_caption": "%s %.3f", "scores": {"class_score": 166.125}, "domain": "pixel"}, {"position": {"minX": 366.21875, "minY": 1.72265625, "maxX": 377.859375, "maxY": 18.23828125}, "class_id": 0, "box_caption": "%s %.3f", "scores": {"class_score": 8.3359375}, "domain": "pixel"}, {"position": {"minX": 381.3125, "minY": 603.953125, "maxX": 411.53125, "maxY": 644.796875}, "class_id": 0, "box_caption": "%s %.3f", "scores": {"class_score": 625.5}, "domain": "pixel"}, {"position": {"minX": 411.69140625, "minY": 589.3046875, "maxX": 423.26171875, "maxY": 605.8984375}, "class_id": 0, "box_caption": "%s %.3f", "scores": {"class_score": 596.0}, "domain": "pixel"}, {"position": {"minX": 426.33203125, "minY": 568.4140625, "maxX": 437.26953125, "maxY": 586.3359375}, "class_id": 0, "box_caption": "%s %.3f", "scores": {"class_score": 575.5}, "domain": "pixel"}, {"position": {"minX": 514.09375, "minY": 165.390625, "maxX": 526.578125, "maxY": 183.890625}, "class_id": 0, "box_caption": "%s %.3f", "scores": {"class_score": 173.0}, "domain": "pixel"}, {"position": {"minX": 358.30859375, "minY": 1.328125, "maxX": 370.62890625, "maxY": 17.40625}, "class_id": 0, "box_caption": "%s %.3f", "scores": {"class_score": 6.98828125}, "domain": "pixel"}, {"position": {"minX": 292.7265625, "minY": 604.6015625, "maxX": 302.7578125, "maxY": 620.4765625}, "class_id": 0, "box_caption": "%s %.3f", "scores": {"class_score": 612.0}, "domain": "pixel"}, {"position": {"minX": 376.6171875, "minY": 592.37109375, "maxX": 387.7890625, "maxY": 607.86328125}, "class_id": 0, "box_caption": "%s %.3f", "scores": {"class_score": 600.5}, "domain": "pixel"}, {"position": {"minX": 428.17578125, "minY": 8.76171875, "maxX": 441.35546875, "maxY": 25.24609375}, "class_id": 0, "box_caption": "%s %.3f", "scores": {"class_score": 14.78125}, "domain": "pixel"}, {"position": {"minX": 486.265625, "minY": 12.0390625, "maxX": 497.921875, "maxY": 30.3359375}, "class_id": 0, "box_caption": "%s %.3f", "scores": {"class_score": 19.578125}, "domain": "pixel"}, {"position": {"minX": 486.48046875, "minY": 17.0859375, "maxX": 499.33203125, "maxY": 33.2578125}, "class_id": 0, "box_caption": "%s %.3f", "scores": {"class_score": 23.203125}, "domain": "pixel"}, {"position": {"minX": 291.6484375, "minY": 610.2890625, "maxX": 301.6796875, "maxY": 626.6640625}, "class_id": 0, "box_caption": "%s %.3f", "scores": {"class_score": 617.0}, "domain": "pixel"}, {"position": {"minX": 575.89453125, "minY": 50.72265625, "maxX": 586.71484375, "maxY": 65.46484375}, "class_id": 0, "box_caption": "%s %.3f", "scores": {"class_score": 56.65625}, "domain": "pixel"}, {"position": {"minX": 416.328125, "minY": 601.18359375, "maxX": 427.90625, "maxY": 619.02734375}, "class_id": 0, "box_caption": "%s %.3f", "scores": {"class_score": 606.5}, "domain": "pixel"}, {"position": {"minX": 415.546875, "minY": 551.234375, "maxX": 443.609375, "maxY": 587.984375}, "class_id": 0, "box_caption": "%s %.3f", "scores": {"class_score": 565.0}, "domain": "pixel"}, {"position": {"minX": 522.36328125, "minY": 48.33984375, "maxX": 533.38671875, "maxY": 63.23828125}, "class_id": 0, "box_caption": "%s %.3f", "scores": {"class_score": 55.9375}, "domain": "pixel"}, {"position": {"minX": 620.953125, "minY": 33.015625, "maxX": 635.21875, "maxY": 49.5625}, "class_id": 0, "box_caption": "%s %.3f", "scores": {"class_score": 39.46875}, "domain": "pixel"}, {"position": {"minX": 375.53125, "minY": 599.3984375, "maxX": 402.625, "maxY": 632.1484375}, "class_id": 0, "box_caption": "%s %.3f", "scores": {"class_score": 615.0}, "domain": "pixel"}, {"position": {"minX": 290.7578125, "minY": 619.5546875, "maxX": 300.4765625, "maxY": 636.9296875}, "class_id": 0, "box_caption": "%s %.3f", "scores": {"class_score": 627.0}, "domain": "pixel"}, {"position": {"minX": 573.3671875, "minY": 52.84765625, "maxX": 587.3359375, "maxY": 76.94140625}, "class_id": 0, "box_caption": "%s %.3f", "scores": {"class_score": 62.71875}, "domain": "pixel"}, {"position": {"minX": 379.5078125, "minY": 599.6015625, "maxX": 396.5390625, "maxY": 627.6640625}, "class_id": 0, "box_caption": "%s %.3f", "scores": {"class_score": 613.5}, "domain": "pixel"}, {"position": {"minX": 507.75, "minY": 157.2890625, "maxX": 524.734375, "maxY": 184.7109375}, "class_id": 0, "box_caption": "%s %.3f", "scores": {"class_score": 166.5}, "domain": "pixel"}, {"position": {"minX": 565.078125, "minY": 29.271484375, "maxX": 576.015625, "maxY": 46.615234375}, "class_id": 0, "box_caption": "%s %.3f", "scores": {"class_score": 36.59375}, "domain": "pixel"}, {"position": {"minX": 419.921875, "minY": 558.6015625, "maxX": 433.15625, "maxY": 582.8359375}, "class_id": 0, "box_caption": "%s %.3f", "scores": {"class_score": 565.0}, "domain": "pixel"}, {"position": {"minX": 523.2421875, "minY": 52.25, "maxX": 538.625, "maxY": 76.25}, "class_id": 0, "box_caption": "%s %.3f", "scores": {"class_score": 61.625}, "domain": "pixel"}, {"position": {"minX": 409.54296875, "minY": 622.90234375, "maxX": 421.05859375, "maxY": 642.15234375}, "class_id": 0, "box_caption": "%s %.3f", "scores": {"class_score": 632.0}, "domain": "pixel"}, {"position": {"minX": 568.33984375, "minY": 26.71875, "maxX": 579.82421875, "maxY": 41.6953125}, "class_id": 0, "box_caption": "%s %.3f", "scores": {"class_score": 30.984375}, "domain": "pixel"}, {"position": {"minX": 558.8671875, "minY": -38.7578125, "maxX": 671.4921875, "maxY": 113.4921875}, "class_id": 0, "box_caption": "%s %.3f", "scores": {"class_score": 18.234375}, "domain": "pixel"}, {"position": {"minX": 419.68359375, "minY": 547.859375, "maxX": 431.42578125, "maxY": 565.109375}, "class_id": 0, "box_caption": "%s %.3f", "scores": {"class_score": 556.5}, "domain": "pixel"}, {"position": {"minX": 616.33984375, "minY": 34.47265625, "maxX": 631.09765625, "maxY": 50.34765625}, "class_id": 0, "box_caption": "%s %.3f", "scores": {"class_score": 40.46875}, "domain": "pixel"}, {"position": {"minX": 423.515625, "minY": 8.75390625, "maxX": 436.578125, "maxY": 24.53515625}, "class_id": 0, "box_caption": "%s %.3f", "scores": {"class_score": 14.3125}, "domain": "pixel"}, {"position": {"minX": 408.84375, "minY": 562.6796875, "maxX": 440.71875, "maxY": 605.0859375}, "class_id": 0, "box_caption": "%s %.3f", "scores": {"class_score": 580.5}, "domain": "pixel"}, {"position": {"minX": 432.705078125, "minY": 545.34765625, "maxX": 444.478515625, "maxY": 563.64453125}, "class_id": 0, "box_caption": "%s %.3f", "scores": {"class_score": 553.0}, "domain": "pixel"}, {"position": {"minX": 490.94921875, "minY": 17.39453125, "maxX": 503.40234375, "maxY": 33.47265625}, "class_id": 0, "box_caption": "%s %.3f", "scores": {"class_score": 23.640625}, "domain": "pixel"}, {"position": {"minX": 538.869140625, "minY": 56.07421875, "maxX": 548.978515625, "maxY": 70.37890625}, "class_id": 0, "box_caption": "%s %.3f", "scores": {"class_score": 62.5625}, "domain": "pixel"}, {"position": {"minX": 370.36328125, "minY": 2.890625, "maxX": 381.34765625, "maxY": 18.6953125}, "class_id": 0, "box_caption": "%s %.3f", "scores": {"class_score": 9.78125}, "domain": "pixel"}, {"position": {"minX": 481.046875, "minY": 17.40234375, "maxX": 494.296875, "maxY": 33.22265625}, "class_id": 0, "box_caption": "%s %.3f", "scores": {"class_score": 23.375}, "domain": "pixel"}, {"position": {"minX": 532.8125, "minY": 48.55859375, "maxX": 543.46875, "maxY": 62.76953125}, "class_id": 0, "box_caption": "%s %.3f", "scores": {"class_score": 53.6875}, "domain": "pixel"}, {"position": {"minX": 571.97265625, "minY": 57.611328125, "maxX": 586.12890625, "maxY": 82.923828125}, "class_id": 0, "box_caption": "%s %.3f", "scores": {"class_score": 65.5}, "domain": "pixel"}, {"position": {"minX": 385.796875, "minY": 532.4375, "maxX": 462.234375, "maxY": 667.1875}, "class_id": 0, "box_caption": "%s %.3f", "scores": {"class_score": 597.5}, "domain": "pixel"}, {"position": {"minX": 418.265625, "minY": 542.140625, "maxX": 445.859375, "maxY": 575.640625}, "class_id": 0, "box_caption": "%s %.3f", "scores": {"class_score": 556.5}, "domain": "pixel"}, {"position": {"minX": 589.41015625, "minY": 33.3828125, "maxX": 602.50390625, "maxY": 49.125}, "class_id": 0, "box_caption": "%s %.3f", "scores": {"class_score": 37.59375}, "domain": "pixel"}, {"position": {"minX": 384.58984375, "minY": 608.5859375, "maxX": 404.02734375, "maxY": 643.0546875}, "class_id": 0, "box_caption": "%s %.3f", "scores": {"class_score": 620.0}, "domain": "pixel"}, {"position": {"minX": 521.984375, "minY": 56.962890625, "maxX": 539.171875, "maxY": 83.634765625}, "class_id": 0, "box_caption": "%s %.3f", "scores": {"class_score": 64.625}, "domain": "pixel"}, {"position": {"minX": 547.5, "minY": -22.875, "maxX": 625.9375, "maxY": 101.375}, "class_id": 0, "box_caption": "%s %.3f", "scores": {"class_score": 39.46875}, "domain": "pixel"}, {"position": {"minX": 374.6484375, "minY": 567.4375, "maxX": 433.7734375, "maxY": 651.125}, "class_id": 0, "box_caption": "%s %.3f", "scores": {"class_score": 613.0}, "domain": "pixel"}, {"position": {"minX": 386.71875, "minY": 470.3125, "maxX": 472.71875, "maxY": 654.5625}, "class_id": 0, "box_caption": "%s %.3f", "scores": {"class_score": 554.0}, "domain": "pixel"}, {"position": {"minX": 292.71484375, "minY": 604.47265625, "maxX": 304.78515625, "maxY": 632.08203125}, "class_id": 0, "box_caption": "%s %.3f", "scores": {"class_score": 614.0}, "domain": "pixel"}, {"position": {"minX": 325.46875, "minY": 124.71484375, "maxX": 338.5625, "maxY": 153.68359375}, "class_id": 0, "box_caption": "%s %.3f", "scores": {"class_score": 133.625}, "domain": "pixel"}, {"position": {"minX": 377.640625, "minY": 595.640625, "maxX": 391.328125, "maxY": 616.984375}, "class_id": 0, "box_caption": "%s %.3f", "scores": {"class_score": 605.0}, "domain": "pixel"}, {"position": {"minX": 300.28515625, "minY": 549.1875, "maxX": 312.16015625, "maxY": 575.1875}, "class_id": 0, "box_caption": "%s %.3f", "scores": {"class_score": 559.0}, "domain": "pixel"}, {"position": {"minX": 574.09765625, "minY": 3.109375, "maxX": 584.64453125, "maxY": 19.46875}, "class_id": 0, "box_caption": "%s %.3f", "scores": {"class_score": 8.984375}, "domain": "pixel"}, {"position": {"minX": 421.4375, "minY": -52.46875, "maxX": 669.1875, "maxY": 233.03125}, "class_id": 0, "box_caption": "%s %.3f", "scores": {"class_score": 77.75}, "domain": "pixel"}, {"position": {"minX": 582.79296875, "minY": 35.734375, "maxX": 595.42578125, "maxY": 51.90625}, "class_id": 0, "box_caption": "%s %.3f", "scores": {"class_score": 39.09375}, "domain": "pixel"}, {"position": {"minX": 509.55859375, "minY": 162.154296875, "maxX": 526.99609375, "maxY": 188.498046875}, "class_id": 0, "box_caption": "%s %.3f", "scores": {"class_score": 171.25}, "domain": "pixel"}, {"position": {"minX": 433.0390625, "minY": 527.828125, "maxX": 444.6328125, "maxY": 543.375}, "class_id": 0, "box_caption": "%s %.3f", "scores": {"class_score": 533.0}, "domain": "pixel"}, {"position": {"minX": 454.890625, "minY": 11.24609375, "maxX": 468.59375, "maxY": 27.62109375}, "class_id": 0, "box_caption": "%s %.3f", "scores": {"class_score": 17.71875}, "domain": "pixel"}, {"position": {"minX": 425.75390625, "minY": 537.921875, "maxX": 440.31640625, "maxY": 566.203125}, "class_id": 0, "box_caption": "%s %.3f", "scores": {"class_score": 548.5}, "domain": "pixel"}, {"position": {"minX": 390.09765625, "minY": 592.15234375, "maxX": 401.05078125, "maxY": 605.84765625}, "class_id": 0, "box_caption": "%s %.3f", "scores": {"class_score": 597.0}, "domain": "pixel"}, {"position": {"minX": 565.515625, "minY": 603.98046875, "maxX": 579.375, "maxY": 633.15234375}, "class_id": 0, "box_caption": "%s %.3f", "scores": {"class_score": 617.5}, "domain": "pixel"}, {"position": {"minX": 540.28125, "minY": 25.6171875, "maxX": 552.6328125, "maxY": 41.03125}, "class_id": 0, "box_caption": "%s %.3f", "scores": {"class_score": 31.125}, "domain": "pixel"}, {"position": {"minX": 299.44140625, "minY": 597.4140625, "maxX": 309.33984375, "maxY": 612.9609375}, "class_id": 0, "box_caption": "%s %.3f", "scores": {"class_score": 604.0}, "domain": "pixel"}, {"position": {"minX": 421.44140625, "minY": 564.40625, "maxX": 432.82421875, "maxY": 591.671875}, "class_id": 0, "box_caption": "%s %.3f", "scores": {"class_score": 565.0}, "domain": "pixel"}, {"position": {"minX": 490.734375, "minY": 11.25, "maxX": 502.7265625, "maxY": 30.25}, "class_id": 0, "box_caption": "%s %.3f", "scores": {"class_score": 19.6875}, "domain": "pixel"}, {"position": {"minX": 301.5, "minY": 615.796875, "maxX": 311.6796875, "maxY": 633.3125}, "class_id": 0, "box_caption": "%s %.3f", "scores": {"class_score": 624.0}, "domain": "pixel"}, {"position": {"minX": 341.09765625, "minY": 626.91015625, "maxX": 351.50390625, "maxY": 640.98046875}, "class_id": 0, "box_caption": "%s %.3f", "scores": {"class_score": 634.0}, "domain": "pixel"}, {"position": {"minX": 571.29296875, "minY": 21.1796875, "maxX": 582.80859375, "maxY": 38.0546875}, "class_id": 0, "box_caption": "%s %.3f", "scores": {"class_score": 27.75}, "domain": "pixel"}, {"position": {"minX": 351.359375, "minY": 0.53125, "maxX": 364.046875, "maxY": 16.1953125}, "class_id": 0, "box_caption": "%s %.3f", "scores": {"class_score": 6.25390625}, "domain": "pixel"}, {"position": {"minX": 405.7421875, "minY": 610.25390625, "maxX": 419.6484375, "maxY": 642.94140625}, "class_id": 0, "box_caption": "%s %.3f", "scores": {"class_score": 614.5}, "domain": "pixel"}, {"position": {"minX": 459.5078125, "minY": 12.3671875, "maxX": 472.765625, "maxY": 28.7734375}, "class_id": 0, "box_caption": "%s %.3f", "scores": {"class_score": 18.703125}, "domain": "pixel"}, {"position": {"minX": 479.5390625, "minY": 14.0859375, "maxX": 491.4140625, "maxY": 30.4140625}, "class_id": 0, "box_caption": "%s %.3f", "scores": {"class_score": 21.53125}, "domain": "pixel"}, {"position": {"minX": 385.4921875, "minY": 611.111328125, "maxX": 400.1015625, "maxY": 634.876953125}, "class_id": 0, "box_caption": "%s %.3f", "scores": {"class_score": 619.5}, "domain": "pixel"}, {"position": {"minX": 580.8828125, "minY": 48.203125, "maxX": 591.5703125, "maxY": 62.875}, "class_id": 0, "box_caption": "%s %.3f", "scores": {"class_score": 52.21875}, "domain": "pixel"}, {"position": {"minX": 567.396484375, "minY": 42.1953125, "maxX": 597.693359375, "maxY": 81.6015625}, "class_id": 0, "box_caption": "%s %.3f", "scores": {"class_score": 61.84375}, "domain": "pixel"}, {"position": {"minX": 300.28515625, "minY": 553.72265625, "maxX": 310.66015625, "maxY": 569.06640625}, "class_id": 0, "box_caption": "%s %.3f", "scores": {"class_score": 560.0}, "domain": "pixel"}, {"position": {"minX": 397.453125, "minY": 571.671875, "maxX": 439.765625, "maxY": 629.890625}, "class_id": 0, "box_caption": "%s %.3f", "scores": {"class_score": 600.0}, "domain": "pixel"}, {"position": {"minX": 535.57421875, "minY": 26.71484375, "maxX": 547.87890625, "maxY": 41.65234375}, "class_id": 0, "box_caption": "%s %.3f", "scores": {"class_score": 31.65625}, "domain": "pixel"}, {"position": {"minX": 504.2578125, "minY": 167.95703125, "maxX": 516.1328125, "maxY": 185.53515625}, "class_id": 0, "box_caption": "%s %.3f", "scores": {"class_score": 176.75}, "domain": "pixel"}, {"position": {"minX": 436.3671875, "minY": 528.515625, "maxX": 446.9453125, "maxY": 543.1875}, "class_id": 0, "box_caption": "%s %.3f", "scores": {"class_score": 533.0}, "domain": "pixel"}, {"position": {"minX": 400.1875, "minY": -120.1875, "maxX": 688.6875, "maxY": 171.5625}, "class_id": 0, "box_caption": "%s %.3f", "scores": {"class_score": 59.9375}, "domain": "pixel"}, {"position": {"minX": 390.30078125, "minY": 613.0234375, "maxX": 408.62890625, "maxY": 644.3203125}, "class_id": 0, "box_caption": "%s %.3f", "scores": {"class_score": 624.5}, "domain": "pixel"}, {"position": {"minX": 408.54296875, "minY": 586.40234375, "maxX": 427.13671875, "maxY": 632.30859375}, "class_id": 0, "box_caption": "%s %.3f", "scores": {"class_score": 596.0}, "domain": "pixel"}, {"position": {"minX": 381.7578125, "minY": 606.2890625, "maxX": 427.5703125, "maxY": 656.5078125}, "class_id": 0, "box_caption": "%s %.3f", "scores": {"class_score": 610.0}, "domain": "pixel"}, {"position": {"minX": 291.2890625, "minY": 610.9375, "maxX": 304.0390625, "maxY": 641.875}, "class_id": 0, "box_caption": "%s %.3f", "scores": {"class_score": 619.0}, "domain": "pixel"}, {"position": {"minX": 360.5625, "minY": 499.90625, "maxX": 453.25, "maxY": 685.90625}, "class_id": 0, "box_caption": "%s %.3f", "scores": {"class_score": 592.0}, "domain": "pixel"}, {"position": {"minX": 343.6875, "minY": -72.375, "maxX": 628.1875, "maxY": 255.125}, "class_id": 0, "box_caption": "%s %.3f", "scores": {"class_score": 80.25}, "domain": "pixel"}, {"position": {"minX": 378.265625, "minY": 590.78125, "maxX": 401.859375, "maxY": 626.78125}, "class_id": 0, "box_caption": "%s %.3f", "scores": {"class_score": 612.5}, "domain": "pixel"}, {"position": {"minX": 434.53125, "minY": 9.75, "maxX": 448.1953125, "maxY": 26.25}, "class_id": 0, "box_caption": "%s %.3f", "scores": {"class_score": 16.046875}, "domain": "pixel"}, {"position": {"minX": 575.3046875, "minY": 9.8046875, "maxX": 586.1796875, "maxY": 26.1796875}, "class_id": 0, "box_caption": "%s %.3f", "scores": {"class_score": 15.8046875}, "domain": "pixel"}, {"position": {"minX": 373.953125, "minY": 543.5625, "maxX": 466.828125, "maxY": 705.5625}, "class_id": 0, "box_caption": "%s %.3f", "scores": {"class_score": 599.5}, "domain": "pixel"}, {"position": {"minX": 416.984375, "minY": 571.2578125, "maxX": 430.875, "maxY": 605.3828125}, "class_id": 0, "box_caption": "%s %.3f", "scores": {"class_score": 572.5}, "domain": "pixel"}, {"position": {"minX": 562.46875, "minY": 23.8984375, "maxX": 573.09375, "maxY": 39.2734375}, "class_id": 0, "box_caption": "%s %.3f", "scores": {"class_score": 32.5}, "domain": "pixel"}, {"position": {"minX": 536.96875, "minY": -69.078125, "maxX": 649.15625, "maxY": 156.421875}, "class_id": 0, "box_caption": "%s %.3f", "scores": {"class_score": 3.46875}, "domain": "pixel"}, {"position": {"minX": 403.1171875, "minY": 593.6640625, "maxX": 426.5546875, "maxY": 647.6015625}, "class_id": 0, "box_caption": "%s %.3f", "scores": {"class_score": 606.5}, "domain": "pixel"}, {"position": {"minX": 481.375, "minY": -48.96875, "maxX": 724.625, "maxY": 224.28125}, "class_id": 0, "box_caption": "%s %.3f", "scores": {"class_score": 70.75}, "domain": "pixel"}, {"position": {"minX": 596.71875, "minY": 33.4921875, "maxX": 610.9609375, "maxY": 50.0859375}, "class_id": 0, "box_caption": "%s %.3f", "scores": {"class_score": 38.59375}, "domain": "pixel"}, {"position": {"minX": 295.4453125, "minY": 605.05078125, "maxX": 310.8515625, "maxY": 633.70703125}, "class_id": 0, "box_caption": "%s %.3f", "scores": {"class_score": 618.0}, "domain": "pixel"}, {"position": {"minX": 510.65625, "minY": 152.4921875, "maxX": 522.578125, "maxY": 169.1171875}, "class_id": 0, "box_caption": "%s %.3f", "scores": {"class_score": 157.625}, "domain": "pixel"}, {"position": {"minX": 524.734375, "minY": 21.484375, "maxX": 535.8125, "maxY": 36.140625}, "class_id": 0, "box_caption": "%s %.3f", "scores": {"class_score": 27.90625}, "domain": "pixel"}, {"position": {"minX": 584.16015625, "minY": 29.2109375, "maxX": 597.41796875, "maxY": 45.3515625}, "class_id": 0, "box_caption": "%s %.3f", "scores": {"class_score": 33.625}, "domain": "pixel"}, {"position": {"minX": 423.673828125, "minY": 553.49609375, "maxX": 438.978515625, "maxY": 587.33984375}, "class_id": 0, "box_caption": "%s %.3f", "scores": {"class_score": 561.5}, "domain": "pixel"}, {"position": {"minX": 376.296875, "minY": 589.609375, "maxX": 408.828125, "maxY": 643.578125}, "class_id": 0, "box_caption": "%s %.3f", "scores": {"class_score": 622.5}, "domain": "pixel"}, {"position": {"minX": 501.0859375, "minY": 159.765625, "maxX": 525.3984375, "maxY": 191.703125}, "class_id": 0, "box_caption": "%s %.3f", "scores": {"class_score": 170.875}, "domain": "pixel"}, {"position": {"minX": 297.52734375, "minY": 546.26953125, "maxX": 313.09765625, "maxY": 579.51953125}, "class_id": 0, "box_caption": "%s %.3f", "scores": {"class_score": 557.0}, "domain": "pixel"}, {"position": {"minX": 417.55859375, "minY": 562.0703125, "maxX": 432.75390625, "maxY": 597.1015625}, "class_id": 0, "box_caption": "%s %.3f", "scores": {"class_score": 567.0}, "domain": "pixel"}, {"position": {"minX": 294.13671875, "minY": 594.21875, "maxX": 306.47265625, "maxY": 622.28125}, "class_id": 0, "box_caption": "%s %.3f", "scores": {"class_score": 604.0}, "domain": "pixel"}, {"position": {"minX": 306.9375, "minY": 495.5625, "maxX": 522.0625, "maxY": 720.8125}, "class_id": 0, "box_caption": "%s %.3f", "scores": {"class_score": 584.5}, "domain": "pixel"}, {"position": {"minX": 338.375, "minY": 545.875, "maxX": 446.1875, "maxY": 686.125}, "class_id": 0, "box_caption": "%s %.3f", "scores": {"class_score": 621.0}, "domain": "pixel"}, {"position": {"minX": 555.46484375, "minY": 12.96875, "maxX": 586.54296875, "maxY": 56.46875}, "class_id": 0, "box_caption": "%s %.3f", "scores": {"class_score": 26.703125}, "domain": "pixel"}, {"position": {"minX": 519.84375, "minY": 42.453125, "maxX": 541.71875, "maxY": 72.859375}, "class_id": 0, "box_caption": "%s %.3f", "scores": {"class_score": 55.59375}, "domain": "pixel"}, {"position": {"minX": 373.9453125, "minY": 594.21875, "maxX": 395.8203125, "maxY": 622.875}, "class_id": 0, "box_caption": "%s %.3f", "scores": {"class_score": 605.5}, "domain": "pixel"}, {"position": {"minX": 501.34375, "minY": 158.1640625, "maxX": 529.53125, "maxY": 210.2265625}, "class_id": 0, "box_caption": "%s %.3f", "scores": {"class_score": 177.0}, "domain": "pixel"}, {"position": {"minX": 568.8046875, "minY": 46.1953125, "maxX": 595.1328125, "maxY": 97.1015625}, "class_id": 0, "box_caption": "%s %.3f", "scores": {"class_score": 62.5625}, "domain": "pixel"}, {"position": {"minX": 515.90625, "minY": 49.5, "maxX": 541.65625, "maxY": 92.8125}, "class_id": 0, "box_caption": "%s %.3f", "scores": {"class_score": 66.625}, "domain": "pixel"}, {"position": {"minX": 607.28515625, "minY": 34.6171875, "maxX": 622.58984375, "maxY": 52.2734375}, "class_id": 0, "box_caption": "%s %.3f", "scores": {"class_score": 40.34375}, "domain": "pixel"}, {"position": {"minX": 326.2890625, "minY": 131.33984375, "maxX": 336.9453125, "maxY": 146.33203125}, "class_id": 0, "box_caption": "%s %.3f", "scores": {"class_score": 137.375}, "domain": "pixel"}, {"position": {"minX": 399.25, "minY": 597.9921875, "maxX": 409.0, "maxY": 612.9453125}, "class_id": 0, "box_caption": "%s %.3f", "scores": {"class_score": 605.0}, "domain": "pixel"}, {"position": {"minX": 415.515625, "minY": -2.4453125, "maxX": 449.390625, "maxY": 37.3359375}, "class_id": 0, "box_caption": "%s %.3f", "scores": {"class_score": 7.7421875}, "domain": "pixel"}, {"position": {"minX": 470.359375, "minY": 93.03125, "maxX": 568.984375, "maxY": 243.15625}, "class_id": 0, "box_caption": "%s %.3f", "scores": {"class_score": 151.0}, "domain": "pixel"}, {"position": {"minX": 470.859375, "minY": 606.8828125, "maxX": 487.609375, "maxY": 636.0546875}, "class_id": 0, "box_caption": "%s %.3f", "scores": {"class_score": 615.5}, "domain": "pixel"}, {"position": {"minX": 478.921875, "minY": 1.015625, "maxX": 507.359375, "maxY": 43.703125}, "class_id": 0, "box_caption": "%s %.3f", "scores": {"class_score": 11.484375}, "domain": "pixel"}, {"position": {"minX": 405.640625, "minY": 492.28125, "maxX": 505.390625, "maxY": 694.15625}, "class_id": 0, "box_caption": "%s %.3f", "scores": {"class_score": 582.5}, "domain": "pixel"}, {"position": {"minX": 461.3203125, "minY": 16.09765625, "maxX": 475.3828125, "maxY": 32.80078125}, "class_id": 0, "box_caption": "%s %.3f", "scores": {"class_score": 21.375}, "domain": "pixel"}, {"position": {"minX": 527.861328125, "minY": 46.35546875, "maxX": 557.970703125, "maxY": 86.73046875}, "class_id": 0, "box_caption": "%s %.3f", "scores": {"class_score": 61.71875}, "domain": "pixel"}, {"position": {"minX": 362.765625, "minY": 595.671875, "maxX": 410.046875, "maxY": 655.203125}, "class_id": 0, "box_caption": "%s %.3f", "scores": {"class_score": 626.5}, "domain": "pixel"}, {"position": {"minX": 407.796875, "minY": 552.3125, "maxX": 448.546875, "maxY": 612.21875}, "class_id": 0, "box_caption": "%s %.3f", "scores": {"class_score": 578.5}, "domain": "pixel"}, {"position": {"minX": 415.34765625, "minY": 570.65625, "maxX": 434.34765625, "maxY": 616.875}, "class_id": 0, "box_caption": "%s %.3f", "scores": {"class_score": 577.0}, "domain": "pixel"}, {"position": {"minX": 400.06640625, "minY": 5.0703125, "maxX": 411.43359375, "maxY": 20.5703125}, "class_id": 0, "box_caption": "%s %.3f", "scores": {"class_score": 12.171875}, "domain": "pixel"}, {"position": {"minX": 409.85546875, "minY": 594.390625, "maxX": 423.20703125, "maxY": 615.578125}, "class_id": 0, "box_caption": "%s %.3f", "scores": {"class_score": 601.0}, "domain": "pixel"}, {"position": {"minX": 620.94140625, "minY": 39.17578125, "maxX": 635.27734375, "maxY": 57.50390625}, "class_id": 0, "box_caption": "%s %.3f", "scores": {"class_score": 44.59375}, "domain": "pixel"}, {"position": {"minX": 408.6875, "minY": 580.2265625, "maxX": 426.671875, "maxY": 618.1640625}, "class_id": 0, "box_caption": "%s %.3f", "scores": {"class_score": 589.0}, "domain": "pixel"}, {"position": {"minX": 565.5859375, "minY": 55.30078125, "maxX": 588.4765625, "maxY": 89.14453125}, "class_id": 0, "box_caption": "%s %.3f", "scores": {"class_score": 65.8125}, "domain": "pixel"}, {"position": {"minX": 381.087890625, "minY": 584.7734375, "maxX": 416.369140625, "maxY": 662.1484375}, "class_id": 0, "box_caption": "%s %.3f", "scores": {"class_score": 623.5}, "domain": "pixel"}, {"position": {"minX": 383.734375, "minY": 499.890625, "maxX": 477.859375, "maxY": 746.640625}, "class_id": 0, "box_caption": "%s %.3f", "scores": {"class_score": 597.0}, "domain": "pixel"}, {"position": {"minX": 445.8828125, "minY": 11.37890625, "maxX": 459.9921875, "maxY": 27.37109375}, "class_id": 0, "box_caption": "%s %.3f", "scores": {"class_score": 17.59375}, "domain": "pixel"}, {"position": {"minX": 410.3984375, "minY": 580.7265625, "maxX": 422.4921875, "maxY": 597.8203125}, "class_id": 0, "box_caption": "%s %.3f", "scores": {"class_score": 588.5}, "domain": "pixel"}, {"position": {"minX": 391.640625, "minY": -4.90625, "maxX": 421.921875, "maxY": 33.25}, "class_id": 0, "box_caption": "%s %.3f", "scores": {"class_score": 4.2734375}, "domain": "pixel"}, {"position": {"minX": 534.11328125, "minY": 24.18359375, "maxX": 545.26171875, "maxY": 38.72265625}, "class_id": 0, "box_caption": "%s %.3f", "scores": {"class_score": 30.75}, "domain": "pixel"}, {"position": {"minX": 527.66796875, "minY": 25.64453125, "maxX": 539.89453125, "maxY": 41.01953125}, "class_id": 0, "box_caption": "%s %.3f", "scores": {"class_score": 30.15625}, "domain": "pixel"}, {"position": {"minX": 428.55078125, "minY": 530.796875, "maxX": 448.83203125, "maxY": 568.765625}, "class_id": 0, "box_caption": "%s %.3f", "scores": {"class_score": 551.5}, "domain": "pixel"}, {"position": {"minX": 513.626953125, "minY": 35.6484375, "maxX": 557.220703125, "maxY": 108.4609375}, "class_id": 0, "box_caption": "%s %.3f", "scores": {"class_score": 62.6875}, "domain": "pixel"}, {"position": {"minX": 491.71875, "minY": -90.96875, "maxX": 638.21875, "maxY": 176.53125}, "class_id": 0, "box_caption": "%s %.3f", "scores": {"class_score": -4.1875}, "domain": "pixel"}, {"position": {"minX": 470.3203125, "minY": 17.6015625, "maxX": 484.4765625, "maxY": 34.1640625}, "class_id": 0, "box_caption": "%s %.3f", "scores": {"class_score": 23.015625}, "domain": "pixel"}, {"position": {"minX": 331.83203125, "minY": 616.4140625, "maxX": 358.97265625, "maxY": 649.9453125}, "class_id": 0, "box_caption": "%s %.3f", "scores": {"class_score": 635.5}, "domain": "pixel"}, {"position": {"minX": 339.4765625, "minY": -12.11328125, "maxX": 376.8828125, "maxY": 33.73046875}, "class_id": 0, "box_caption": "%s %.3f", "scores": {"class_score": 0.71484375}, "domain": "pixel"}, {"position": {"minX": 394.7109375, "minY": 443.8671875, "maxX": 515.1484375, "maxY": 659.6171875}, "class_id": 0, "box_caption": "%s %.3f", "scores": {"class_score": 505.25}, "domain": "pixel"}, {"position": {"minX": 534.09765625, "minY": 37.0078125, "maxX": 545.98046875, "maxY": 52.9765625}, "class_id": 0, "box_caption": "%s %.3f", "scores": {"class_score": 39.6875}, "domain": "pixel"}, {"position": {"minX": 454.2578125, "minY": 15.76171875, "maxX": 468.6953125, "maxY": 33.38671875}, "class_id": 0, "box_caption": "%s %.3f", "scores": {"class_score": 21.703125}, "domain": "pixel"}, {"position": {"minX": 424.9453125, "minY": 529.4453125, "maxX": 443.3984375, "maxY": 560.9765625}, "class_id": 0, "box_caption": "%s %.3f", "scores": {"class_score": 542.5}, "domain": "pixel"}, {"position": {"minX": 295.58203125, "minY": 589.6640625, "maxX": 306.57421875, "maxY": 606.2109375}, "class_id": 0, "box_caption": "%s %.3f", "scores": {"class_score": 595.5}, "domain": "pixel"}, {"position": {"minX": 469.31640625, "minY": 12.8046875, "maxX": 482.82421875, "maxY": 29.9296875}, "class_id": 0, "box_caption": "%s %.3f", "scores": {"class_score": 19.71875}, "domain": "pixel"}, {"position": {"minX": 385.39453125, "minY": 574.59375, "maxX": 420.36328125, "maxY": 638.0625}, "class_id": 0, "box_caption": "%s %.3f", "scores": {"class_score": 612.0}, "domain": "pixel"}, {"position": {"minX": 293.5625, "minY": 372.59375, "maxX": 455.4375, "maxY": 807.09375}, "class_id": 0, "box_caption": "%s %.3f", "scores": {"class_score": 601.0}, "domain": "pixel"}, {"position": {"minX": 296.419921875, "minY": 591.9921875, "maxX": 310.279296875, "maxY": 622.3984375}, "class_id": 0, "box_caption": "%s %.3f", "scores": {"class_score": 606.0}, "domain": "pixel"}, {"position": {"minX": 278.0, "minY": -83.90625, "maxX": 563.0, "maxY": 263.34375}, "class_id": 0, "box_caption": "%s %.3f", "scores": {"class_score": 76.1875}, "domain": "pixel"}, {"position": {"minX": 520.37109375, "minY": 18.9765625, "maxX": 532.69140625, "maxY": 34.6796875}, "class_id": 0, "box_caption": "%s %.3f", "scores": {"class_score": 25.9375}, "domain": "pixel"}, {"position": {"minX": 487.296875, "minY": 4.9375, "maxX": 498.6875, "maxY": 21.375}, "class_id": 0, "box_caption": "%s %.3f", "scores": {"class_score": 11.703125}, "domain": "pixel"}, {"position": {"minX": 472.125, "minY": 611.671875, "maxX": 483.640625, "maxY": 626.921875}, "class_id": 0, "box_caption": "%s %.3f", "scores": {"class_score": 617.5}, "domain": "pixel"}, {"position": {"minX": 400.474609375, "minY": 588.70703125, "maxX": 430.677734375, "maxY": 661.95703125}, "class_id": 0, "box_caption": "%s %.3f", "scores": {"class_score": 606.5}, "domain": "pixel"}, {"position": {"minX": 553.375, "minY": -82.03125, "maxX": 689.625, "maxY": 171.21875}, "class_id": 0, "box_caption": "%s %.3f", "scores": {"class_score": 1.0}, "domain": "pixel"}, {"position": {"minX": 293.5703125, "minY": 548.44921875, "maxX": 313.7890625, "maxY": 588.38671875}, "class_id": 0, "box_caption": "%s %.3f", "scores": {"class_score": 558.5}, "domain": "pixel"}, {"position": {"minX": 351.7734375, "minY": -12.11328125, "maxX": 389.3671875, "maxY": 33.54296875}, "class_id": 0, "box_caption": "%s %.3f", "scores": {"class_score": -0.015625}, "domain": "pixel"}, {"position": {"minX": 570.5546875, "minY": 3.03515625, "maxX": 582.2734375, "maxY": 19.17578125}, "class_id": 0, "box_caption": "%s %.3f", "scores": {"class_score": 9.296875}, "domain": "pixel"}, {"position": {"minX": 323.625, "minY": 426.125, "maxX": 506.625, "maxY": 666.875}, "class_id": 0, "box_caption": "%s %.3f", "scores": {"class_score": 542.5}, "domain": "pixel"}, {"position": {"minX": 565.88671875, "minY": 609.40625, "maxX": 576.79296875, "maxY": 625.1484375}, "class_id": 0, "box_caption": "%s %.3f", "scores": {"class_score": 615.5}, "domain": "pixel"}, {"position": {"minX": 403.4140625, "minY": 6.46484375, "maxX": 414.6640625, "maxY": 21.25390625}, "class_id": 0, "box_caption": "%s %.3f", "scores": {"class_score": 12.5546875}, "domain": "pixel"}, {"position": {"minX": 288.875, "minY": 593.5546875, "maxX": 306.203125, "maxY": 635.4296875}, "class_id": 0, "box_caption": "%s %.3f", "scores": {"class_score": 609.5}, "domain": "pixel"}, {"position": {"minX": 256.5625, "minY": 489.125, "maxX": 463.6875, "maxY": 728.875}, "class_id": 0, "box_caption": "%s %.3f", "scores": {"class_score": 564.0}, "domain": "pixel"}, {"position": {"minX": 349.90625, "minY": 447.359375, "maxX": 468.53125, "maxY": 656.734375}, "class_id": 0, "box_caption": "%s %.3f", "scores": {"class_score": 532.5}, "domain": "pixel"}, {"position": {"minX": 246.0, "minY": 526.390625, "maxX": 346.625, "maxY": 705.765625}, "class_id": 0, "box_caption": "%s %.3f", "scores": {"class_score": 591.5}, "domain": "pixel"}, {"position": {"minX": 568.88671875, "minY": 11.421875, "maxX": 580.50390625, "maxY": 27.609375}, "class_id": 0, "box_caption": "%s %.3f", "scores": {"class_score": 16.59375}, "domain": "pixel"}, {"position": {"minX": 500.4375, "minY": 141.8203125, "maxX": 533.375, "maxY": 182.1328125}, "class_id": 0, "box_caption": "%s %.3f", "scores": {"class_score": 161.75}, "domain": "pixel"}, {"position": {"minX": 417.8359375, "minY": 532.78125, "maxX": 451.0234375, "maxY": 602.28125}, "class_id": 0, "box_caption": "%s %.3f", "scores": {"class_score": 557.5}, "domain": "pixel"}, {"position": {"minX": 476.1875, "minY": 69.640625, "maxX": 594.125, "maxY": 266.015625}, "class_id": 0, "box_caption": "%s %.3f", "scores": {"class_score": 138.125}, "domain": "pixel"}, {"position": {"minX": 567.2734375, "minY": 599.15625, "maxX": 584.3046875, "maxY": 632.25}, "class_id": 0, "box_caption": "%s %.3f", "scores": {"class_score": 617.0}, "domain": "pixel"}, {"position": {"minX": 427.19140625, "minY": 578.21484375, "maxX": 437.83984375, "maxY": 595.30859375}, "class_id": 0, "box_caption": "%s %.3f", "scores": {"class_score": 585.0}, "domain": "pixel"}, {"position": {"minX": 350.53125, "minY": 472.4375, "maxX": 593.28125, "maxY": 736.6875}, "class_id": 0, "box_caption": "%s %.3f", "scores": {"class_score": 580.0}, "domain": "pixel"}, {"position": {"minX": 384.9375, "minY": -8.6015625, "maxX": 428.6875, "maxY": 41.7109375}, "class_id": 0, "box_caption": "%s %.3f", "scores": {"class_score": 3.921875}, "domain": "pixel"}, {"position": {"minX": 436.2734375, "minY": 565.0546875, "maxX": 446.8671875, "maxY": 581.7890625}, "class_id": 0, "box_caption": "%s %.3f", "scores": {"class_score": 572.0}, "domain": "pixel"}, {"position": {"minX": 560.03125, "minY": 32.65625, "maxX": 573.1875, "maxY": 50.375}, "class_id": 0, "box_caption": "%s %.3f", "scores": {"class_score": 39.75}, "domain": "pixel"}, {"position": {"minX": 379.59375, "minY": 538.1875, "maxX": 450.71875, "maxY": 639.0625}, "class_id": 0, "box_caption": "%s %.3f", "scores": {"class_score": 593.0}, "domain": "pixel"}, {"position": {"minX": 287.3984375, "minY": 596.46484375, "maxX": 319.5546875, "maxY": 658.15234375}, "class_id": 0, "box_caption": "%s %.3f", "scores": {"class_score": 616.5}, "domain": "pixel"}, {"position": {"minX": 480.15625, "minY": -37.953125, "maxX": 591.53125, "maxY": 149.671875}, "class_id": 0, "box_caption": "%s %.3f", "scores": {"class_score": 32.9375}, "domain": "pixel"}, {"position": {"minX": 290.48828125, "minY": 597.921875, "maxX": 302.02734375, "maxY": 613.84375}, "class_id": 0, "box_caption": "%s %.3f", "scores": {"class_score": 605.5}, "domain": "pixel"}, {"position": {"minX": 567.05859375, "minY": 47.0, "maxX": 577.95703125, "maxY": 63.0}, "class_id": 0, "box_caption": "%s %.3f", "scores": {"class_score": 53.6875}, "domain": "pixel"}, {"position": {"minX": 368.05078125, "minY": 578.8515625, "maxX": 407.08203125, "maxY": 623.7890625}, "class_id": 0, "box_caption": "%s %.3f", "scores": {"class_score": 604.0}, "domain": "pixel"}, {"position": {"minX": 366.33984375, "minY": 5.783203125, "maxX": 379.75390625, "maxY": 24.486328125}, "class_id": 0, "box_caption": "%s %.3f", "scores": {"class_score": 12.5078125}, "domain": "pixel"}, {"position": {"minX": 594.34765625, "minY": 28.296875, "maxX": 608.73828125, "maxY": 48.03125}, "class_id": 0, "box_caption": "%s %.3f", "scores": {"class_score": 35.9375}, "domain": "pixel"}, {"position": {"minX": 433.9921875, "minY": 531.21875, "maxX": 446.2890625, "maxY": 549.4375}, "class_id": 0, "box_caption": "%s %.3f", "scores": {"class_score": 542.5}, "domain": "pixel"}, {"position": {"minX": 320.9765625, "minY": 125.759765625, "maxX": 337.8359375, "maxY": 161.916015625}, "class_id": 0, "box_caption": "%s %.3f", "scores": {"class_score": 137.75}, "domain": "pixel"}, {"position": {"minX": 489.98046875, "minY": 5.2421875, "maxX": 501.40234375, "maxY": 21.7890625}, "class_id": 0, "box_caption": "%s %.3f", "scores": {"class_score": 12.1328125}, "domain": "pixel"}, {"position": {"minX": 504.63671875, "minY": 139.9140625, "maxX": 546.76171875, "maxY": 202.6953125}, "class_id": 0, "box_caption": "%s %.3f", "scores": {"class_score": 173.25}, "domain": "pixel"}, {"position": {"minX": 578.66796875, "minY": 2.34375, "maxX": 590.80078125, "maxY": 21.03125}, "class_id": 0, "box_caption": "%s %.3f", "scores": {"class_score": 9.8046875}, "domain": "pixel"}, {"position": {"minX": 525.92578125, "minY": 38.015625, "maxX": 538.10546875, "maxY": 54.390625}, "class_id": 0, "box_caption": "%s %.3f", "scores": {"class_score": 41.0625}, "domain": "pixel"}, {"position": {"minX": 160.59375, "minY": -87.3125, "maxX": 414.46875, "maxY": 262.9375}, "class_id": 0, "box_caption": "%s %.3f", "scores": {"class_score": 86.875}, "domain": "pixel"}, {"position": {"minX": 549.921875, "minY": 1.03125, "maxX": 594.484375, "maxY": 63.8125}, "class_id": 0, "box_caption": "%s %.3f", "scores": {"class_score": 23.1875}, "domain": "pixel"}, {"position": {"minX": 349.84375, "minY": 19.8125, "maxX": 610.09375, "maxY": 412.0625}, "class_id": 0, "box_caption": "%s %.3f", "scores": {"class_score": 197.0}, "domain": "pixel"}, {"position": {"minX": 423.78125, "minY": 23.65625, "maxX": 662.28125, "maxY": 408.15625}, "class_id": 0, "box_caption": "%s %.3f", "scores": {"class_score": 189.125}, "domain": "pixel"}, {"position": {"minX": 200.5625, "minY": -149.625, "maxX": 505.5625, "maxY": 193.625}, "class_id": 0, "box_caption": "%s %.3f", "scores": {"class_score": 39.0}, "domain": "pixel"}, {"position": {"minX": 379.68359375, "minY": 579.296875, "maxX": 450.49609375, "maxY": 685.109375}, "class_id": 0, "box_caption": "%s %.3f", "scores": {"class_score": 596.5}, "domain": "pixel"}, {"position": {"minX": 512.984375, "minY": 26.0546875, "maxX": 544.0625, "maxY": 88.6171875}, "class_id": 0, "box_caption": "%s %.3f", "scores": {"class_score": 57.46875}, "domain": "pixel"}, {"position": {"minX": 454.078125, "minY": 47.453125, "maxX": 555.078125, "maxY": 256.828125}, "class_id": 0, "box_caption": "%s %.3f", "scores": {"class_score": 131.5}, "domain": "pixel"}, {"position": {"minX": 323.51171875, "minY": 124.71484375, "maxX": 345.90234375, "maxY": 163.58984375}, "class_id": 0, "box_caption": "%s %.3f", "scores": {"class_score": 135.625}, "domain": "pixel"}, {"position": {"minX": 222.625, "minY": -38.375, "maxX": 479.375, "maxY": 341.875}, "class_id": 0, "box_caption": "%s %.3f", "scores": {"class_score": 144.875}, "domain": "pixel"}, {"position": {"minX": 437.03125, "minY": 570.921875, "maxX": 447.609375, "maxY": 587.75}, "class_id": 0, "box_caption": "%s %.3f", "scores": {"class_score": 578.0}, "domain": "pixel"}, {"position": {"minX": 404.11328125, "minY": 8.22265625, "maxX": 416.77734375, "maxY": 24.55078125}, "class_id": 0, "box_caption": "%s %.3f", "scores": {"class_score": 14.40625}, "domain": "pixel"}, {"position": {"minX": 621.84375, "minY": -1.015625, "maxX": 634.828125, "maxY": 19.015625}, "class_id": 0, "box_caption": "%s %.3f", "scores": {"class_score": 6.98828125}, "domain": "pixel"}, {"position": {"minX": 414.09375, "minY": 538.4609375, "maxX": 437.84375, "maxY": 595.4296875}, "class_id": 0, "box_caption": "%s %.3f", "scores": {"class_score": 557.5}, "domain": "pixel"}, {"position": {"minX": 326.0625, "minY": 118.3828125, "maxX": 343.546875, "maxY": 154.4765625}, "class_id": 0, "box_caption": "%s %.3f", "scores": {"class_score": 133.75}, "domain": "pixel"}, {"position": {"minX": 413.9765625, "minY": 9.9921875, "maxX": 427.4296875, "maxY": 25.6796875}, "class_id": 0, "box_caption": "%s %.3f", "scores": {"class_score": 15.5625}, "domain": "pixel"}, {"position": {"minX": 99.78125, "minY": -83.25, "maxX": 346.65625, "maxY": 258.5}, "class_id": 0, "box_caption": "%s %.3f", "scores": {"class_score": 88.75}, "domain": "pixel"}, {"position": {"minX": 420.8125, "minY": 518.625, "maxX": 450.390625, "maxY": 587.0625}, "class_id": 0, "box_caption": "%s %.3f", "scores": {"class_score": 542.0}, "domain": "pixel"}, {"position": {"minX": 337.03125, "minY": 624.05078125, "maxX": 349.765625, "maxY": 639.38671875}, "class_id": 0, "box_caption": "%s %.3f", "scores": {"class_score": 631.0}, "domain": "pixel"}, {"position": {"minX": 81.0, "minY": -146.28125, "maxX": 364.75, "maxY": 189.71875}, "class_id": 0, "box_caption": "%s %.3f", "scores": {"class_score": 42.0}, "domain": "pixel"}, {"position": {"minX": 559.78125, "minY": 598.2421875, "maxX": 579.671875, "maxY": 640.8671875}, "class_id": 0, "box_caption": "%s %.3f", "scores": {"class_score": 616.5}, "domain": "pixel"}, {"position": {"minX": 493.775390625, "minY": 134.6328125, "maxX": 543.806640625, "maxY": 237.2578125}, "class_id": 0, "box_caption": "%s %.3f", "scores": {"class_score": 171.0}, "domain": "pixel"}, {"position": {"minX": 417.330078125, "minY": 610.296875, "maxX": 428.744140625, "maxY": 627.921875}, "class_id": 0, "box_caption": "%s %.3f", "scores": {"class_score": 616.5}, "domain": "pixel"}, {"position": {"minX": 428.55078125, "minY": 14.99609375, "maxX": 442.98828125, "maxY": 33.85546875}, "class_id": 0, "box_caption": "%s %.3f", "scores": {"class_score": 20.53125}, "domain": "pixel"}, {"position": {"minX": 255.765625, "minY": 478.21875, "maxX": 367.578125, "maxY": 721.71875}, "class_id": 0, "box_caption": "%s %.3f", "scores": {"class_score": 552.0}, "domain": "pixel"}, {"position": {"minX": 298.3046875, "minY": 549.4140625, "maxX": 309.9453125, "maxY": 565.5234375}, "class_id": 0, "box_caption": "%s %.3f", "scores": {"class_score": 556.0}, "domain": "pixel"}, {"position": {"minX": 485.40625, "minY": 34.5, "maxX": 724.28125, "maxY": 397.75}, "class_id": 0, "box_caption": "%s %.3f", "scores": {"class_score": 183.875}, "domain": "pixel"}, {"position": {"minX": 546.8046875, "minY": 25.8671875, "maxX": 560.0625, "maxY": 41.8984375}, "class_id": 0, "box_caption": "%s %.3f", "scores": {"class_score": 31.109375}, "domain": "pixel"}, {"position": {"minX": 284.03125, "minY": 23.625, "maxX": 543.78125, "maxY": 406.375}, "class_id": 0, "box_caption": "%s %.3f", "scores": {"class_score": 204.25}, "domain": "pixel"}, {"position": {"minX": 291.94140625, "minY": 545.5703125, "maxX": 318.81640625, "maxY": 611.8203125}, "class_id": 0, "box_caption": "%s %.3f", "scores": {"class_score": 564.0}, "domain": "pixel"}, {"position": {"minX": 322.00390625, "minY": 606.3515625, "maxX": 369.09765625, "maxY": 669.5078125}, "class_id": 0, "box_caption": "%s %.3f", "scores": {"class_score": 640.0}, "domain": "pixel"}, {"position": {"minX": 588.39453125, "minY": 42.875, "maxX": 600.74609375, "maxY": 60.34375}, "class_id": 0, "box_caption": "%s %.3f", "scores": {"class_score": 46.0625}, "domain": "pixel"}, {"position": {"minX": 516.1484375, "minY": 43.484375, "maxX": 549.0234375, "maxY": 77.859375}, "class_id": 0, "box_caption": "%s %.3f", "scores": {"class_score": 58.75}, "domain": "pixel"}, {"position": {"minX": 378.53515625, "minY": -19.3203125, "maxX": 437.84765625, "maxY": 53.1796875}, "class_id": 0, "box_caption": "%s %.3f", "scores": {"class_score": 1.4375}, "domain": "pixel"}, {"position": {"minX": 406.0546875, "minY": 525.484375, "maxX": 461.6171875, "maxY": 640.796875}, "class_id": 0, "box_caption": "%s %.3f", "scores": {"class_score": 568.5}, "domain": "pixel"}, {"position": {"minX": 604.890625, "minY": 29.9140625, "maxX": 619.953125, "maxY": 49.1015625}, "class_id": 0, "box_caption": "%s %.3f", "scores": {"class_score": 37.625}, "domain": "pixel"}, {"position": {"minX": 622.59375, "minY": 7.57421875, "maxX": 636.640625, "maxY": 29.80859375}, "class_id": 0, "box_caption": "%s %.3f", "scores": {"class_score": 17.0}, "domain": "pixel"}, {"position": {"minX": 305.771484375, "minY": 612.109375, "maxX": 316.646484375, "maxY": 628.1875}, "class_id": 0, "box_caption": "%s %.3f", "scores": {"class_score": 619.5}, "domain": "pixel"}, {"position": {"minX": 416.85546875, "minY": 539.9921875, "maxX": 429.03515625, "maxY": 557.9609375}, "class_id": 0, "box_caption": "%s %.3f", "scores": {"class_score": 548.0}, "domain": "pixel"}, {"position": {"minX": 435.109375, "minY": 556.0234375, "maxX": 445.9609375, "maxY": 574.1953125}, "class_id": 0, "box_caption": "%s %.3f", "scores": {"class_score": 563.0}, "domain": "pixel"}, {"position": {"minX": 300.240234375, "minY": 549.32421875, "maxX": 320.412109375, "maxY": 577.13671875}, "class_id": 0, "box_caption": "%s %.3f", "scores": {"class_score": 565.5}, "domain": "pixel"}], "class_labels": {"0": "Ant"}}