{"box_data": [{"position": {"minX": 353.8359375, "minY": 329.55859375, "maxX": 371.1796875, "maxY": 347.23046875}, "class_id": 0, "box_caption": "%s %.3f", "scores": {"class_score": 333.75}, "domain": "pixel"}, {"position": {"minX": 333.60546875, "minY": 285.953125, "maxX": 343.81640625, "maxY": 299.390625}, "class_id": 0, "box_caption": "%s %.3f", "scores": {"class_score": 291.5}, "domain": "pixel"}, {"position": {"minX": 344.3046875, "minY": 287.01171875, "maxX": 352.6015625, "maxY": 300.18359375}, "class_id": 0, "box_caption": "%s %.3f", "scores": {"class_score": 296.25}, "domain": "pixel"}, {"position": {"minX": 336.1640625, "minY": 314.19140625, "maxX": 349.2578125, "maxY": 323.64453125}, "class_id": 0, "box_caption": "%s %.3f", "scores": {"class_score": 317.75}, "domain": "pixel"}, {"position": {"minX": 334.26953125, "minY": 286.9921875, "maxX": 348.71484375, "maxY": 300.1640625}, "class_id": 0, "box_caption": "%s %.3f", "scores": {"class_score": 294.0}, "domain": "pixel"}, {"position": {"minX": 337.453125, "minY": 286.515625, "maxX": 350.984375, "maxY": 304.390625}, "class_id": 0, "box_caption": "%s %.3f", "scores": {"class_score": 298.75}, "domain": "pixel"}, {"position": {"minX": 350.3125, "minY": 326.8125, "maxX": 368.3125, "maxY": 344.84375}, "class_id": 0, "box_caption": "%s %.3f", "scores": {"class_score": 326.75}, "domain": "pixel"}, {"position": {"minX": 333.0859375, "minY": 285.7734375, "maxX": 348.4140625, "maxY": 306.6015625}, "class_id": 0, "box_caption": "%s %.3f", "scores": {"class_score": 299.5}, "domain": "pixel"}, {"position": {"minX": 306.6875, "minY": 282.828125, "maxX": 395.5, "maxY": 346.296875}, "class_id": 0, "box_caption": "%s %.3f", "scores": {"class_score": 312.75}, "domain": "pixel"}, {"position": {"minX": 328.109375, "minY": 287.43359375, "maxX": 340.640625, "maxY": 299.87890625}, "class_id": 0, "box_caption": "%s %.3f", "scores": {"class_score": 295.25}, "domain": "pixel"}, {"position": {"minX": 345.01171875, "minY": 284.33984375, "maxX": 354.64453125, "maxY": 298.00390625}, "class_id": 0, "box_caption": "%s %.3f", "scores": {"class_score": 292.0}, "domain": "pixel"}, {"position": {"minX": 336.74609375, "minY": 276.33203125, "maxX": 348.62890625, "maxY": 288.04296875}, "class_id": 0, "box_caption": "%s %.3f", "scores": {"class_score": 279.75}, "domain": "pixel"}, {"position": {"minX": 336.453125, "minY": 318.796875, "maxX": 353.171875, "maxY": 335.578125}, "class_id": 0, "box_caption": "%s %.3f", "scores": {"class_score": 329.0}, "domain": "pixel"}, {"position": {"minX": 343.5546875, "minY": 299.265625, "maxX": 352.7421875, "maxY": 313.1640625}, "class_id": 0, "box_caption": "%s %.3f", "scores": {"class_score": 305.25}, "domain": "pixel"}, {"position": {"minX": 632.837890625, "minY": 446.962890625, "maxX": 638.919921875, "maxY": 462.650390625}, "class_id": 0, "box_caption": "%s %.3f", "scores": {"class_score": 449.25}, "domain": "pixel"}, {"position": {"minX": 583.12890625, "minY": 356.92578125, "maxX": 593.80859375, "maxY": 372.48046875}, "class_id": 0, "box_caption": "%s %.3f", "scores": {"class_score": 362.5}, "domain": "pixel"}], "class_labels": {"0": "Ant"}}